databricks_filestore_uploader/main.py
databricks_filestore_uploader/toolchain/filestore_utils.py
databricks_filestore_uploader/toolchain/option_utils.py
databricks_filestore_uploader-0.1.0.dist-info/LICENSE
databricks_filestore_uploader-0.1.0.dist-info/WHEEL
databricks_filestore_uploader-0.1.0.dist-info/METADATA
databricks_filestore_uploader-0.1.0.dist-info/RECORD
