Metadata-Version: 2.1
Name: databricks-filestore-uploader
Version: 0.1.0
Summary: A quick filetree uploader for the databricks filestore, local to cloud.
Home-page: https://github.com/anthonybench/databricks-filestore-uploader
License: GNU GPL
Keywords: databricks,filestore,convenienece
Author: anthonybench
Author-email: anthonybenchyep@gmail.com
Requires-Python: >=3.10,<4.0
Classifier: License :: Other/Proprietary License
Classifier: Programming Language :: Python :: 3
Classifier: Programming Language :: Python :: 3.10
Project-URL: Repository, https://github.com/anthonybench/databricks-filestore-uploader
